kwdataengineer/__init__.py
kwdataengineer/conf.py
kwdataengineer/datamodels.py
kwdataengineer/dba.py
kwdataengineer/devguide.py
kwdataengineer/dworker.py
kwdataengineer/Lib/__init__.py
kwdataengineer/Lib/dtype.py
kwdataengineer/Lib/finder.py
kwdataengineer/Lib/metadata.py
trddt/__init__.py
trddt/config.py
kwdataengineer-0.1.0.dist-info/LICENSE
kwdataengineer-0.1.0.dist-info/METADATA
kwdataengineer-0.1.0.dist-info/WHEEL
kwdataengineer-0.1.0.dist-info/top_level.txt
kwdataengineer-0.1.0.dist-info/RECORD
