Metadata-Version: 2.1
Name: kwdataengineer
Version: 0.1.0
Summary: Kiwoom DataEngineer
Home-page: https://github.com/innovata/KiwoomDataEngineer
Author: innovata sambong
Author-email: iinnovata@gmail.com
Classifier: Programming Language :: Python :: 3
Classifier: License :: OSI Approved :: MIT License
Classifier: Operating System :: OS Independent
Requires-Python: >=3.8
License-File: LICENSE
